[
  {
    "id": 1,
    "name": "White Black",
    "phone": "0931555666",
    "payment": "digital payment"
  },
  {
    "id": 2,
    "name": "王大明",
    "phone": "0955678123",
    "payment": "ATM"
  },
  {
    "id": 3,
    "name": "Evans May",
    "phone": "0909222111",
    "payment": "digital payment"
  },
  {
    "id": 4,
    "name": "雷神風",
    "phone": "0951324423",
    "payment": "ATM"
  },
  {
    "id": 5,
    "name": "葉青雲",
    "phone": "0967855944",
    "payment": "digital payment"
  },
  {
    "id": 6,
    "name": "Mello",
    "phone": "0907955833",
    "payment": "ATM"
  },
  {
    "id": 7,
    "name": "Shaco",
    "phone": "0915666222",
    "payment": "digital payment"
  }
]
